<?xml version="1.0" encoding="ISO-8859-1"?>
<!-- edited with XMLSPY v2004 rel. 2 U (http://www.xmlspy.com) by lcollins (Firaxis Games) -->
<!-- Sid Meier's Civilization 4 -->
<!-- -->
<Civ4GameText xmlns="http://www.firaxis.com">

	<TEXT>
		<Tag>TXT_KEY_LEADER_JIMMU</Tag>
		<English>Jimmu</English>
		<French>
			<Text>Jimmu</Text>
			<Gender>Male</Gender>
			<Plural>0</Plural>
		</French>
		<German>
			<Text>Jimmu</Text>
			<Gender>Male</Gender>
			<Plural>0</Plural>
		</German>
		<Italian>
			<Text>Jimmu</Text>
			<Gender>Male</Gender>
			<Plural>0</Plural>
		</Italian>
		<Spanish>
			<Text>Jimmu</Text>
			<Gender>Male</Gender>
			<Plural>0</Plural>
		</Spanish>
	</TEXT>
	<TEXT>
		<Tag>TXT_KEY_LEADER_MEIJI</Tag>
		<English>Meiji</English>
		<French>
			<Text>Meiji</Text>
			<Gender>Male</Gender>
			<Plural>0</Plural>
		</French>
		<German>
			<Text>Meiji</Text>
			<Gender>Male</Gender>
			<Plural>0</Plural>
		</German>
		<Italian>
			<Text>Meiji</Text>
			<Gender>Male</Gender>
			<Plural>0</Plural>
		</Italian>
		<Spanish>
			<Text>Meiji</Text>
			<Gender>Male</Gender>
			<Plural>0</Plural>
		</Spanish>
	</TEXT>
	<TEXT>
		<Tag>TXT_KEY_LEADER_AKBAR</Tag>
		<English>Akbar</English>
		<French>
			<Text>Akbar</Text>
			<Gender>Male</Gender>
			<Plural>0</Plural>
		</French>
		<German>
			<Text>Akbar</Text>
			<Gender>Male</Gender>
			<Plural>0</Plural>
		</German>
		<Italian>
			<Text>Akbar</Text>
			<Gender>Male</Gender>
			<Plural>0</Plural>
		</Italian>
		<Spanish>
			<Text>Akbar</Text>
			<Gender>Male</Gender>
			<Plural>0</Plural>
		</Spanish>
	</TEXT>
	<TEXT>
		<Tag>TXT_KEY_LEADER_GILGAMESH</Tag>
		<English>Sargon</English>
		<French>
			<Text>Sargon</Text>
			<Gender>Male</Gender>
			<Plural>0</Plural>
		</French>
		<German>
			<Text>Sargon</Text>
			<Gender>Male</Gender>
			<Plural>0</Plural>
		</German>
		<Italian>
			<Text>Sargon</Text>
			<Gender>Male</Gender>
			<Plural>0</Plural>
		</Italian>
		<Spanish>
			<Text>Sargon</Text>
			<Gender>Male</Gender>
			<Plural>0</Plural>
		</Spanish>
	</TEXT>
	<TEXT>
		<Tag>TXT_KEY_LEADER_HATSHEPSUT</Tag>
		<English>Cleopatra</English>
		<French>
			<Text>Cleopatra</Text>
			<Gender>Male</Gender>
			<Plural>0</Plural>
		</French>
		<German>
			<Text>Cleopatra</Text>
			<Gender>Male</Gender>
			<Plural>0</Plural>
		</German>
		<Italian>
			<Text>Cleopatra</Text>
			<Gender>Male</Gender>
			<Plural>0</Plural>
		</Italian>
		<Spanish>
			<Text>Cleopatra</Text>
			<Gender>Male</Gender>
			<Plural>0</Plural>
		</Spanish>
	</TEXT>
	<TEXT>
		<Tag>TXT_KEY_LEADER_BRENNUS</Tag>
		<English>Alfred</English>
		<French>
			<Text>Alfred</Text>
			<Gender>Male</Gender>
			<Plural>0</Plural>
		</French>
		<German>
			<Text>Alfred</Text>
			<Gender>Male</Gender>
			<Plural>0</Plural>
		</German>
		<Italian>
			<Text>Alfred</Text>
			<Gender>Male</Gender>
			<Plural>0</Plural>
		</Italian>
		<Spanish>
			<Text>Alfred</Text>
			<Gender>Male</Gender>
			<Plural>0</Plural>
		</Spanish>
	</TEXT>
	<TEXT>
		<Tag>TXT_KEY_LEADER_HIRAM</Tag>
		<English>Hiram</English>
		<French>
			<Text>Hiram</Text>
			<Gender>Male</Gender>
			<Plural>0</Plural>
		</French>
		<German>
			<Text>Hiram</Text>
			<Gender>Male</Gender>
			<Plural>0</Plural>
		</German>
		<Italian>
			<Text>Hiram</Text>
			<Gender>Male</Gender>
			<Plural>0</Plural>
		</Italian>
		<Spanish>
			<Text>Hiram</Text>
			<Gender>Male</Gender>
			<Plural>0</Plural>
		</Spanish>
	</TEXT>
	<TEXT>
		<Tag>TXT_KEY_LEADER_HAILE_SELASSIE</Tag>
		<English>Haile Selassie</English>
		<French>
			<Text>Haile Selassie</Text>
			<Gender>Male</Gender>
			<Plural>0</Plural>
		</French>
		<German>
			<Text>Haile Selassie</Text>
			<Gender>Male</Gender>
			<Plural>0</Plural>
		</German>
		<Italian>
			<Text>Haile Selassie</Text>
			<Gender>Male</Gender>
			<Plural>0</Plural>
		</Italian>
		<Spanish>
			<Text>Haile Selassie</Text>
			<Gender>Male</Gender>
			<Plural>0</Plural>
		</Spanish>
	</TEXT>
	<TEXT>
		<Tag>TXT_KEY_LEADER_GUSTAV</Tag>
		<English>Gustav Adolph</English>
		<French>
			<Text>Gustav Adolph</Text>
			<Gender>Male</Gender>
			<Plural>0</Plural>
		</French>
		<German>
			<Text>Gustav Adolph</Text>
			<Gender>Male</Gender>
			<Plural>0</Plural>
		</German>
		<Italian>
			<Text>Gustav Adolph</Text>
			<Gender>Male</Gender>
			<Plural>0</Plural>
		</Italian>
		<Spanish>
			<Text>Gustav Adolph</Text>
			<Gender>Male</Gender>
			<Plural>0</Plural>
		</Spanish>
	</TEXT>
	<TEXT>
		<Tag>TXT_KEY_LEADER_ABU_BAKR</Tag>
		<English>Abu Bakr</English>
		<French>
			<Text>Abu Bakr</Text>
			<Gender>Male</Gender>
			<Plural>0</Plural>
		</French>
		<German>
			<Text>Abu Bakr</Text>
			<Gender>Male</Gender>
			<Plural>0</Plural>
		</German>
		<Italian>
			<Text>Abu Bakr</Text>
			<Gender>Male</Gender>
			<Plural>0</Plural>
		</Italian>
		<Spanish>
			<Text>Abu Bakr</Text>
			<Gender>Male</Gender>
			<Plural>0</Plural>
		</Spanish>
	</TEXT>
	<TEXT>
		<Tag>TXT_KEY_LEADER_MONGKUT</Tag>
		<English>Mongkut</English>
		<French>
			<Text>Mongkut</Text>
			<Gender>Male</Gender>
			<Plural>0</Plural>
		</French>
		<German>
			<Text>Mongkut</Text>
			<Gender>Male</Gender>
			<Plural>0</Plural>
		</German>
		<Italian>
			<Text>Mongkut</Text>
			<Gender>Male</Gender>
			<Plural>0</Plural>
		</Italian>
		<Spanish>
			<Text>Mongkut</Text>
			<Gender>Male</Gender>
			<Plural>0</Plural>
		</Spanish>
	</TEXT>
	<TEXT>
		<Tag>TXT_KEY_LEADER_ELISHAT</Tag>
		<English>Elishat</English>
		<French>
			<Text>Elishat</Text>
			<Gender>Female</Gender>
			<Plural>0</Plural>
		</French>
		<German>
			<Text>Elishat</Text>
			<Gender>Female</Gender>
			<Plural>0</Plural>
		</German>
		<Italian>
			<Text>Elishat</Text>
			<Gender>Female</Gender>
			<Plural>0</Plural>
		</Italian>
		<Spanish>
			<Text>Elishat</Text>
			<Gender>Female</Gender>
			<Plural>0</Plural>
		</Spanish>
	</TEXT>
	<TEXT>
		<Tag>TXT_KEY_LEADER_PHILIP</Tag>
		<English>Philip II</English>
		<French>
			<Text>Philippe II</Text>
			<Gender>Male</Gender>
			<Plural>0</Plural>
		</French>
		<German>
			<Text>Philipp II.</Text>
			<Gender>Male</Gender>
			<Plural>0</Plural>
		</German>
		<Italian>
			<Text>Filippo II</Text>
			<Gender>Male</Gender>
			<Plural>0</Plural>
		</Italian>
		<Spanish>
			<Text>Felipe II</Text>
			<Gender>Male</Gender>
			<Plural>0</Plural>
		</Spanish>
	</TEXT>
	<TEXT>
		<Tag>TXT_KEY_LEADER_BARBAROSSA</Tag>
		<English>Frederick Barbarossa</English>
		<French>
			<Text>Frédéric Barberousse</Text>
			<Gender>Male</Gender>
			<Plural>0</Plural>
		</French>
		<German>
			<Text>Friedrich Barbarossa</Text>
			<Gender>Male</Gender>
			<Plural>0</Plural>
		</German>
		<Italian>
			<Text>Federico Barbarossa</Text>
			<Gender>Male</Gender>
			<Plural>0</Plural>
		</Italian>
		<Spanish>
			<Text>Federico Barbarroja</Text>
			<Gender>Male</Gender>
			<Plural>0</Plural>
		</Spanish>
	</TEXT>
	<TEXT>
		<Tag>TXT_KEY_LEADER_CHARLES</Tag>
		<English>Charles V</English>
		<French>
			<Text>Charles V</Text>
			<Gender>Male</Gender>
			<Plural>0</Plural>
		</French>
		<German>
			<Text>Karl V.</Text>
			<Gender>Male</Gender>
			<Plural>0</Plural>
		</German>
		<Italian>
			<Text>Carlo V</Text>
			<Gender>Male</Gender>
			<Plural>0</Plural>
		</Italian>
		<Spanish>
			<Text>Carlos V</Text>
			<Gender>Male</Gender>
			<Plural>0</Plural>
		</Spanish>
	</TEXT>
	<TEXT>
		<Tag>TXT_KEY_LEADER_FRANCIS</Tag>
		<English>Francis I</English>
		<French>
			<Text>Francois I</Text>
			<Gender>Male</Gender>
			<Plural>0</Plural>
		</French>
		<German>
			<Text>Franz I.</Text>
			<Gender>Male</Gender>
			<Plural>0</Plural>
		</German>
		<Italian>
			<Text>Francesco I</Text>
			<Gender>Male</Gender>
			<Plural>0</Plural>
		</Italian>
		<Spanish>
			<Text>Francisco I</Text>
			<Gender>Male</Gender>
			<Plural>0</Plural>
		</Spanish>
	</TEXT>
	<TEXT>
		<Tag>TXT_KEY_LEADER_YAROSLAV</Tag>
		<English>Yaroslav</English>
		<French>
			<Text>Iaroslav</Text>
			<Gender>Male</Gender>
			<Plural>0</Plural>
		</French>
		<German>
			<Text>Jaroslaw</Text>
			<Gender>Male</Gender>
			<Plural>0</Plural>
		</German>
		<Italian>
			<Text>Jaroslav</Text>
			<Gender>Male</Gender>
			<Plural>0</Plural>
		</Italian>
		<Spanish>
			<Text>Yaroslav</Text>
			<Gender>Male</Gender>
			<Plural>0</Plural>
		</Spanish>
	</TEXT>
	<TEXT>
    		<Tag>TXT_KEY_LEADER_AFONSO</Tag>
    		<English>Afonso Henriques</English>
    		<French>Alphonse Henriques</French>
    		<German>Alfons Henriques</German>
    		<Italian>Alfonso Henriques</Italian>
    		<Spanish>Alfonso Henriques</Spanish>
  	</TEXT>
	<TEXT>
		<Tag>TXT_KEY_LEADER_ATATURK</Tag>
		<English>Atatürk</English>
		<French>
			<Text>Atatürk</Text>
			<Gender>Male</Gender>
			<Plural>0</Plural>
		</French>
		<German>
			<Text>Atatürk</Text>
			<Gender>Male</Gender>
			<Plural>0</Plural>
		</German>
		<Italian>
			<Text>Atatürk</Text>
			<Gender>Male</Gender>
			<Plural>0</Plural>
		</Italian>
		<Spanish>
			<Text>Atatürk</Text>
			<Gender>Male</Gender>
			<Plural>0</Plural>
		</Spanish>
	</TEXT>
	<TEXT>
		<Tag>TXT_KEY_LEADER_MARIA_II</Tag>
		<English>Maria II</English>
		<French>
			<Text>Maria II</Text>
			<Gender>Male</Gender>
			<Plural>0</Plural>
		</French>
		<German>
			<Text>Maria II</Text>
			<Gender>Male</Gender>
			<Plural>0</Plural>
		</German>
		<Italian>
			<Text>Maria II</Text>
			<Gender>Male</Gender>
			<Plural>0</Plural>
		</Italian>
		<Spanish>
			<Text>Maria II</Text>
			<Gender>Male</Gender>
			<Plural>0</Plural>
		</Spanish>
	</TEXT>
	<TEXT>
		<Tag>TXT_KEY_LEADER_HITLER</Tag>
		<English>Hitler</English>
		<French>
			<Text>Hitler</Text>
			<Gender>Male</Gender>
			<Plural>0</Plural>
		</French>
		<German>
			<Text>Hitler</Text>
			<Gender>Male</Gender>
			<Plural>0</Plural>
		</German>
		<Italian>
			<Text>Hitler</Text>
			<Gender>Male</Gender>
			<Plural>0</Plural>
		</Italian>
		<Spanish>
			<Text>Hitler</Text>
			<Gender>Male</Gender>
			<Plural>0</Plural>
		</Spanish>
	</TEXT>
	<TEXT>
		<Tag>TXT_KEY_LEADER_FRANCO</Tag>
		<English>Franco</English>
		<French>
			<Text>Franco</Text>
			<Gender>Male</Gender>
			<Plural>0</Plural>
		</French>
		<German>
			<Text>Franco</Text>
			<Gender>Male</Gender>
			<Plural>0</Plural>
		</German>
		<Italian>
			<Text>Franco</Text>
			<Gender>Male</Gender>
			<Plural>0</Plural>
		</Italian>
		<Spanish>
			<Text>Franco</Text>
			<Gender>Male</Gender>
			<Plural>0</Plural>
		</Spanish>
	</TEXT>

	<TEXT>
		<Tag>TXT_KEY_LEADER_CIXI</Tag>
		<English>Cixi</English>
		<German>Cixi</German>
	</TEXT>
	<TEXT>
		<Tag>TXT_KEY_LEADER_NICHOLAS</Tag>
		<English>Nicholas II</English>
		<German>Nicholas II.</German>
	</TEXT>
	<TEXT>
		<Tag>TXT_KEY_LEADER_CHIANG_KAISHEK</Tag>
		<English>Chiang Kai-Shek</English>
		<German>Chiang Kai-Shek</German>
	</TEXT>
	<TEXT>
		<Tag>TXT_KEY_LEADER_ABBAS</Tag>
		<English>Abbas I</English>
		<German>Abbas I.</German>
	</TEXT>
	<TEXT>
		<Tag>TXT_KEY_LEADER_KHOMEINI</Tag>
		<English>Khomeini</English>
		<German>Chomeini</German>
	</TEXT>



</Civ4GameText>
