<?xml version="1.0" encoding="ISO-8859-1"?>
<!-- edited with XMLSPY v2004 rel. 2 U (http://www.xmlspy.com) by lcollins (Firaxis Games) -->
<!-- Sid Meier's Civilization 4 -->
<!-- -->
<!-- Game Text - Unit Upgrades for Civilopedia -->
<Civ4GameText xmlns="http://www.firaxis.com">
	<TEXT>
		<Tag>TXT_KEY_CIV_CANADA_DESC</Tag>
		<English>The Canadians</English>
	</TEXT>
	<TEXT>
		<Tag>TXT_KEY_CIV_CANADA_DESC_PEOPLES</Tag>
		<English>Canadian Peoples</English>
	</TEXT>
	<TEXT>
		<Tag>TXT_KEY_CIV_CANADA_DESC_DEFAULT</Tag>
		<English>Dominion of Canada</English>
	</TEXT>
	<TEXT>
		<Tag>TXT_KEY_CIV_CANADA_DESC_DEMOCRATIC</Tag>
		<English>Commonwealth of Canada</English>
	</TEXT>
	<TEXT>
		<Tag>TXT_KEY_CIV_CANADA_DESC_COMMUNIST</Tag>
		<English>Canadian Worker's Commonwealth</English>
	</TEXT>
	<TEXT>
		<Tag>TXT_KEY_CIV_CANADA_DESC_FASCIST</Tag>
		<English>Canadian Empire</English>
	</TEXT>
	<TEXT>
		<Tag>TXT_KEY_CIV_CANADA_EMPIRE</Tag>
		<English>Dominion of Canada</English>
	</TEXT>
	<TEXT>
		<Tag>TXT_KEY_CIV_CANADA_NAZI_VASSAL</Tag>
		<English>Reichskommissariat Kanada</English>
	</TEXT>
	<TEXT>
		<Tag>TXT_KEY_CIV_CANADA_SOVIET_VASSAL</Tag>
		<English>Soviet Canada</English>
	</TEXT>
</Civ4GameText>
